api2mdx/__init__.py
api2mdx/admonition_converter.py
api2mdx/api_discovery.py
api2mdx/documentation_generator.py
api2mdx/griffe_integration.py
api2mdx/main.py
api2mdx/mdx_components.py
api2mdx/mdx_renderer.py
api2mdx/meta.py
api2mdx/models.py
api2mdx/parser.py
api2mdx/parser_test.py
api2mdx/tokenizer.py
api2mdx/tokenizer_test.py
api2mdx/type_extractor.py
api2mdx/type_model.py
api2mdx/type_model_test.py
api2mdx/type_urls.py
api2mdx/type_urls_test.py
api2mdx/scripts/__init__.py
api2mdx/scripts/regenerate_snapshots.py
api2mdx-0.2.2.dist-info/licenses/LICENSE
api2mdx-0.2.2.dist-info/METADATA
api2mdx-0.2.2.dist-info/WHEEL
api2mdx-0.2.2.dist-info/entry_points.txt
api2mdx-0.2.2.dist-info/top_level.txt
api2mdx-0.2.2.dist-info/RECORD
