Metadata-Version: 2.4
Name: api2mdx
Version: 0.2.2
Summary: Generate MDX API documentation from Python source code
Author-email: Dandelion Mané <dandelion@mirascope.com>
License-Expression: MIT
Project-URL: Homepage, https://github.com/Mirascope/api2mdx
Project-URL: Repository, https://github.com/Mirascope/api2mdx
Keywords: documentation,api,mdx,python
Classifier: Development Status :: 3 - Alpha
Classifier: Intended Audience :: Developers
Classifier: Programming Language :: Python :: 3
Classifier: Programming Language :: Python :: 3.10
Classifier: Programming Language :: Python :: 3.11
Classifier: Programming Language :: Python :: 3.12
Classifier: Topic :: Documentation
Classifier: Topic :: Software Development :: Documentation
Requires-Python: >=3.10
License-File: LICENSE
Requires-Dist: griffe>=1.7.2
Dynamic: license-file
